fgcz
