Metadata-Version: 1.1
Name: PyFGCZ
Version: 0.5.20
Summary: PyFGCZ contains BioBeamer and FCC python code.
Home-page: https://github.com/fgcz/PyFGCZ
Author: Christian Panse
Author-email: cp@fgcz.ethz.ch
License: GPLv3
Platform: UNKNOWN
Classifier: License :: OSI Approved :: GNU General Public License v3 (GPLv3)
Classifier: Environment :: Console
Classifier: Intended Audience :: Developers
Classifier: Intended Audience :: System Administrators
Classifier: Operating System :: OS Independent
Classifier: Programming Language :: Python :: 2.7
Classifier: Topic :: Scientific/Engineering :: Bio-Informatics
Classifier: Topic :: Utilities
